micropython_mcp9808/__init__.py
micropython_mcp9808/i2c_helpers.py
micropython_mcp9808/mcp9808.py
micropython_mcp9808-0.2.1.dist-info/LICENSE
micropython_mcp9808-0.2.1.dist-info/METADATA
micropython_mcp9808-0.2.1.dist-info/WHEEL
micropython_mcp9808-0.2.1.dist-info/top_level.txt
micropython_mcp9808-0.2.1.dist-info/RECORD
