Metadata-Version: 2.1
Name: micropython-mcp9808
Version: 0.2.1
Summary: MicroPython Driver for the Microchip MCP9808 Temperature Sensor
Author-email: JDM <xxyx@mailmeto.mozmail.com>
License: MIT
Project-URL: Homepage, https://github.com/jposada202020/MicroPython_MCP9808
Keywords: sensor,mcp9808,temperature,microchip,temperature,micropython
Classifier: Intended Audience :: Developers
Classifier: Topic :: Software Development :: Libraries
Classifier: Topic :: Software Development :: Embedded Systems
Classifier: Topic :: System :: Hardware
Classifier: License :: OSI Approved :: MIT License
Classifier: Programming Language :: Python :: Implementation :: MicroPython
License-File: LICENSE
